NSK/__init__.py
NSK/bot/__init__.py
NSK/bot/share_point.py
NSK/bot/web_access.py
NSK/bot/base/__init__.py
NSK/bot/base/bot.py
NSK/bot/base/meta.py
NSK/common/__init__.py
NSK/common/decorator.py
nsk_bot-1.1.0.dist-info/licenses/LICENSE
nsk_bot-1.1.0.dist-info/METADATA
nsk_bot-1.1.0.dist-info/WHEEL
nsk_bot-1.1.0.dist-info/top_level.txt
nsk_bot-1.1.0.dist-info/RECORD
