Metadata-Version: 2.4
Name: NSK-Bot
Version: 1.1.0
Summary: A Python library for NSK automation
Author-email: Văn Ngoc Nhât Huy <nhathuyd4hp@gmail.com>
License: MIT
Requires-Python: >=3.12
License-File: LICENSE
Requires-Dist: build>=1.2.2.post1
Requires-Dist: pandas>=2.2.3
Requires-Dist: pre-commit>=4.2.0
Requires-Dist: pydantic-settings>=2.9.1
Requires-Dist: selenium>=4.32.0
Requires-Dist: twine>=6.1.0
Dynamic: license-file
